{
  "type": "FeatureCollection",
  "features": [
    {
      "type": "Feature",
      "properties": {
        "NAME": "Bemidji Brewing",
        "ADDRESS": "211 America Ave NW",
        "DETAILS": "Tuesday Night Social Event",
        "EVENTHOURS": "7:00 pm - 9:00 pm",
        "HOURS": "4:00 pm - 10:00 pm",
        "DISCOUNT_NOTES": "TBA",
        "URL": "//bemidjibeer.com"
      },
      "geometry": {
        "type": "Point",
        "coordinates": [
          -94.884803,
          47.469900
        ]
      }
    },
    {
      "type": "Feature",
      "properties": {
        "NAME": "J.J.'s Dockside Restaurant & Tavern",
        "ADDRESS": "929 Lake Shore Dr NE",
        "DETAILS": "Wednesday Welcome Reception",
        "EVENTHOURS": "7:00 pm - 9:30 pm",
        "HOURS": "11:00 am - 12:00 am",
        "DISCOUNT_NOTES": "TBA",
        "URL": "//jjsdockside.com"
      },
      "geometry": {
        "type": "Point",
        "coordinates": [
          -94.855242,
          47.463561
        ]
      }
    },
    {
      "type": "Feature",
      "properties": {
        "NAME": "Eagles Club",
        "ADDRESS": "1270 Neilson Ave S",
        "DETAILS": "Thursday Night Social Event",
        "EVENTHOURS": "7:00 pm - 10:00 pm; Shuttle hours: 6:45 pm - 10:15 pm",
        "HOURS": "6:00 am - 12:00 am",
        "DISCOUNT_NOTES": "TBA",
        "URL": "//minnesotaeagles.com/"
      },
      "geometry": {
        "type": "Point",
        "coordinates": [
          -94.862989,
          47.448041
        ]
      }
    }
  ]
}
